bookmark/__init__.py
bookmark/bookmark.py
bookmark/cli.py
bookmark_cli-0.0.4.dist-info/entry_points.txt
bookmark_cli-0.0.4.dist-info/LICENSE
bookmark_cli-0.0.4.dist-info/WHEEL
bookmark_cli-0.0.4.dist-info/METADATA
bookmark_cli-0.0.4.dist-info/RECORD
