Metadata-Version: 2.1
Name: bookmark-cli
Version: 0.0.4
Summary: command line for bookmark
License: MIT
Author: wxnacy
Author-email: wxnacy@gmail.com
Requires-Python: >=3.9,<4.0
Classifier: License :: OSI Approved :: MIT License
Classifier: Programming Language :: Python :: 3
Classifier: Programming Language :: Python :: 3.10
Classifier: Programming Language :: Python :: 3.9
